{
    "table_name": "european_football_2.Player_Attributes",
    "table_fullname": "european_football_2.european_football_2.Player_Attributes",
    "column_names": [
        "id",
        "player_fifa_api_id",
        "player_api_id",
        "date",
        "overall_rating",
        "potential",
        "attacking_work_rate",
        "defensive_work_rate",
        "crossing",
        "finishing",
        "heading_accuracy",
        "short_passing",
        "volleys",
        "dribbling",
        "curve",
        "free_kick_accuracy",
        "long_passing",
        "ball_control",
        "acceleration",
        "sprint_speed",
        "agility",
        "reactions",
        "balance",
        "shot_power",
        "jumping",
        "stamina",
        "strength",
        "long_shots",
        "aggression",
        "interceptions",
        "positioning",
        "vision",
        "penalties",
        "marking",
        "standing_tackle",
        "sliding_tackle",
        "gk_diving",
        "gk_handling",
        "gk_kicking",
        "gk_positioning",
        "gk_reflexes"
    ],
    "column_types": [
        "TEXT",
        "TEXT",
        "TEXT",
        "TEXT",
        "FLOAT",
        "TEXT",
        "TEXT",
        "TEXT",
        "TEXT",
        "FLOAT",
        "FLOAT",
        "TEXT",
        "TEXT",
        "TEXT",
        "TEXT",
        "TEXT",
        "TEXT",
        "TEXT",
        "TEXT",
        "NUMBER",
        "TEXT",
        "TEXT",
        "TEXT",
        "TEXT",
        "TEXT",
        "TEXT",
        "TEXT",
        "TEXT",
        "TEXT",
        "TEXT",
        "TEXT",
        "TEXT",
        "TEXT",
        "TEXT",
        "TEXT",
        "TEXT",
        "TEXT",
        "TEXT",
        "TEXT",
        "TEXT",
        "TEXT"
    ],
    "description": [
        null,
        null,
        null,
        null,
        null,
        null,
        null,
        null,
        null,
        null,
        null,
        null,
        null,
        null,
        null,
        null,
        null,
        null,
        null,
        null,
        null,
        null,
        null,
        null,
        null,
        null,
        null,
        null,
        null,
        null,
        null,
        null,
        null,
        null,
        null,
        null,
        null,
        null,
        null,
        null,
        null
    ],
    "sample_rows": [
        {
            "id": "1",
            "player_fifa_api_id": "218353",
            "player_api_id": "505942",
            "date": "2016-02-18 00:00:00",
            "overall_rating": 67.0,
            "potential": "71",
            "attacking_work_rate": "medium",
            "defensive_work_rate": "medium",
            "crossing": "49",
            "finishing": 44.0,
            "heading_accuracy": 71.0,
            "short_passing": "61",
            "volleys": "44",
            "dribbling": "51",
            "curve": "45",
            "free_kick_accuracy": "39",
            "long_passing": "64",
            "ball_control": "49",
            "acceleration": "60",
            "sprint_speed": 64,
            "agility": "59",
            "reactions": "47",
            "balance": "65",
            "shot_power": "55",
            "jumping": "58",
            "stamina": "54",
            "strength": "76",
            "long_shots": "35",
            "aggression": "71",
            "interceptions": "70",
            "positioning": "45",
            "vision": "54",
            "penalties": "48",
            "marking": "65",
            "standing_tackle": "69",
            "sliding_tackle": "69",
            "gk_diving": "6",
            "gk_handling": "11",
            "gk_kicking": "10",
            "gk_positioning": "8",
            "gk_reflexes": "8"
        },
        {
            "id": "2",
            "player_fifa_api_id": "218353",
            "player_api_id": "505942",
            "date": "2015-11-19 00:00:00",
            "overall_rating": 67.0,
            "potential": "71",
            "attacking_work_rate": "medium",
            "defensive_work_rate": "medium",
            "crossing": "49",
            "finishing": 44.0,
            "heading_accuracy": 71.0,
            "short_passing": "61",
            "volleys": "44",
            "dribbling": "51",
            "curve": "45",
            "free_kick_accuracy": "39",
            "long_passing": "64",
            "ball_control": "49",
            "acceleration": "60",
            "sprint_speed": 64,
            "agility": "59",
            "reactions": "47",
            "balance": "65",
            "shot_power": "55",
            "jumping": "58",
            "stamina": "54",
            "strength": "76",
            "long_shots": "35",
            "aggression": "71",
            "interceptions": "70",
            "positioning": "45",
            "vision": "54",
            "penalties": "48",
            "marking": "65",
            "standing_tackle": "69",
            "sliding_tackle": "69",
            "gk_diving": "6",
            "gk_handling": "11",
            "gk_kicking": "10",
            "gk_positioning": "8",
            "gk_reflexes": "8"
        },
        {
            "id": "3",
            "player_fifa_api_id": "218353",
            "player_api_id": "505942",
            "date": "2015-09-21 00:00:00",
            "overall_rating": 62.0,
            "potential": "66",
            "attacking_work_rate": "medium",
            "defensive_work_rate": "medium",
            "crossing": "49",
            "finishing": 44.0,
            "heading_accuracy": 71.0,
            "short_passing": "61",
            "volleys": "44",
            "dribbling": "51",
            "curve": "45",
            "free_kick_accuracy": "39",
            "long_passing": "64",
            "ball_control": "49",
            "acceleration": "60",
            "sprint_speed": 64,
            "agility": "59",
            "reactions": "47",
            "balance": "65",
            "shot_power": "55",
            "jumping": "58",
            "stamina": "54",
            "strength": "76",
            "long_shots": "35",
            "aggression": "63",
            "interceptions": "41",
            "positioning": "45",
            "vision": "54",
            "penalties": "48",
            "marking": "65",
            "standing_tackle": "66",
            "sliding_tackle": "69",
            "gk_diving": "6",
            "gk_handling": "11",
            "gk_kicking": "10",
            "gk_positioning": "8",
            "gk_reflexes": "8"
        },
        {
            "id": "4",
            "player_fifa_api_id": "218353",
            "player_api_id": "505942",
            "date": "2015-03-20 00:00:00",
            "overall_rating": 61.0,
            "potential": "65",
            "attacking_work_rate": "medium",
            "defensive_work_rate": "medium",
            "crossing": "48",
            "finishing": 43.0,
            "heading_accuracy": 70.0,
            "short_passing": "60",
            "volleys": "43",
            "dribbling": "50",
            "curve": "44",
            "free_kick_accuracy": "38",
            "long_passing": "63",
            "ball_control": "48",
            "acceleration": "60",
            "sprint_speed": 64,
            "agility": "59",
            "reactions": "46",
            "balance": "65",
            "shot_power": "54",
            "jumping": "58",
            "stamina": "54",
            "strength": "76",
            "long_shots": "34",
            "aggression": "62",
            "interceptions": "40",
            "positioning": "44",
            "vision": "53",
            "penalties": "47",
            "marking": "62",
            "standing_tackle": "63",
            "sliding_tackle": "66",
            "gk_diving": "5",
            "gk_handling": "10",
            "gk_kicking": "9",
            "gk_positioning": "7",
            "gk_reflexes": "7"
        },
        {
            "id": "5",
            "player_fifa_api_id": "218353",
            "player_api_id": "505942",
            "date": "2007-02-22 00:00:00",
            "overall_rating": 61.0,
            "potential": "65",
            "attacking_work_rate": "medium",
            "defensive_work_rate": "medium",
            "crossing": "48",
            "finishing": 43.0,
            "heading_accuracy": 70.0,
            "short_passing": "60",
            "volleys": "43",
            "dribbling": "50",
            "curve": "44",
            "free_kick_accuracy": "38",
            "long_passing": "63",
            "ball_control": "48",
            "acceleration": "60",
            "sprint_speed": 64,
            "agility": "59",
            "reactions": "46",
            "balance": "65",
            "shot_power": "54",
            "jumping": "58",
            "stamina": "54",
            "strength": "76",
            "long_shots": "34",
            "aggression": "62",
            "interceptions": "40",
            "positioning": "44",
            "vision": "53",
            "penalties": "47",
            "marking": "62",
            "standing_tackle": "63",
            "sliding_tackle": "66",
            "gk_diving": "5",
            "gk_handling": "10",
            "gk_kicking": "9",
            "gk_positioning": "7",
            "gk_reflexes": "7"
        }
    ]
}
